pprint_star_design_pattern/__init__.py
pprint_star_design_pattern-0.0.2.dist-info/LICENSE.md
pprint_star_design_pattern-0.0.2.dist-info/METADATA
pprint_star_design_pattern-0.0.2.dist-info/WHEEL
pprint_star_design_pattern-0.0.2.dist-info/top_level.txt
pprint_star_design_pattern-0.0.2.dist-info/RECORD
