Metadata-Version: 2.1
Name: pprint-star-design-pattern
Version: 0.0.2
Summary: A module that will help you to print all different types of star pattern
Home-page: https://pypi.org/user/vikas_bhaskar_vooradi/
Author: Vikas Bhaskar Vooradi
Author-email: vikasvooradi.devs@gmail.com
License: MIT
Keywords: Design patterns,pprint_star_design_pattern,Automation,setuptools,development
Platform: UNKNOWN
Classifier: Development Status :: 3 - Alpha
Classifier: Intended Audience :: Developers
Classifier: Topic :: Software Development :: Build Tools
Classifier: Operating System :: OS Independent
Classifier: License :: OSI Approved :: MIT License
Classifier: Programming Language :: Python :: 3
Requires-Python: >=3
License-File: LICENSE.md
